amazon_braket_pennylane_plugin-1.34.0.dist-info/licenses/LICENSE
amazon_braket_pennylane_plugin-1.34.0.dist-info/licenses/NOTICE
braket/pennylane_plugin/__init__.py
braket/pennylane_plugin/_version.py
braket/pennylane_plugin/ahs_device.py
braket/pennylane_plugin/ahs_translation.py
braket/pennylane_plugin/braket_device.py
braket/pennylane_plugin/ops.py
braket/pennylane_plugin/translation.py
amazon_braket_pennylane_plugin-1.34.0.dist-info/METADATA
amazon_braket_pennylane_plugin-1.34.0.dist-info/WHEEL
amazon_braket_pennylane_plugin-1.34.0.dist-info/entry_points.txt
amazon_braket_pennylane_plugin-1.34.0.dist-info/top_level.txt
amazon_braket_pennylane_plugin-1.34.0.dist-info/RECORD
