Metadata-Version: 2.4
Name: amazon-braket-pennylane-plugin
Version: 1.34.0
Summary: An open source framework for using Amazon Braket devices with the PennyLane quantum machine learning library
Home-page: https://github.com/amazon-braket/amazon-braket-pennylane-plugin-python
Author: Amazon Web Services
License: Apache License 2.0
Keywords: Amazon AWS Quantum
Classifier: Development Status :: 5 - Production/Stable
Classifier: Intended Audience :: Developers
Classifier: Natural Language :: English
Classifier: License :: OSI Approved :: Apache Software License
Classifier: Programming Language :: Python
Classifier: Programming Language :: Python :: 3.11
Classifier: Programming Language :: Python :: 3.12
Classifier: Programming Language :: Python :: 3.13
Requires-Python: >= 3.11
License-File: LICENSE
License-File: NOTICE
Requires-Dist: amazon-braket-sdk>=1.97.0
Requires-Dist: autoray>=0.6.11
Requires-Dist: pennylane>=0.44.0
Provides-Extra: test
Requires-Dist: docutils>=0.19; extra == "test"
Requires-Dist: flaky; extra == "test"
Requires-Dist: pre-commit; extra == "test"
Requires-Dist: pylint>=3.1.0; extra == "test"
Requires-Dist: pytest; extra == "test"
Requires-Dist: pytest-benchmark; extra == "test"
Requires-Dist: pytest-cov; extra == "test"
Requires-Dist: pytest-mock; extra == "test"
Requires-Dist: pytest-rerunfailures<16.0; extra == "test"
Requires-Dist: pytest-xdist; extra == "test"
Requires-Dist: ruff; extra == "test"
Requires-Dist: sphinx; extra == "test"
Requires-Dist: sphinx-automodapi; extra == "test"
Requires-Dist: sphinx-rtd-theme; extra == "test"
Requires-Dist: sphinxcontrib-apidoc; extra == "test"
Requires-Dist: tox; extra == "test"
Requires-Dist: torch>2; extra == "test"
Dynamic: author
Dynamic: classifier
Dynamic: description
Dynamic: description-content-type
Dynamic: home-page
Dynamic: keywords
Dynamic: license
Dynamic: license-file
Dynamic: provides-extra
Dynamic: requires-dist
Dynamic: requires-python
Dynamic: summary
